invenio_assets/__init__.py
invenio_assets/cli.py
invenio_assets/collect.py
invenio_assets/ext.py
invenio_assets/proxies.py
invenio_assets/webpack.py
invenio_assets/assets/.babelrc
invenio_assets/assets/.eslintignore
invenio_assets/assets/.eslintrc.js
invenio_assets/assets/package.json
invenio_assets/assets/pnpm-workspace.yaml
invenio_assets/assets/rspack-package.json
invenio_assets/assets/build/rspack.config.js
invenio_assets/assets/build/webpack.config.js
invenio_assets/assets/patches/semantic-ui-less+2.5.0.patch
invenio_assets-4.2.1.dist-info/licenses/AUTHORS.rst
invenio_assets-4.2.1.dist-info/licenses/LICENSE
invenio_assets-4.2.1.dist-info/METADATA
invenio_assets-4.2.1.dist-info/WHEEL
invenio_assets-4.2.1.dist-info/entry_points.txt
invenio_assets-4.2.1.dist-info/top_level.txt
invenio_assets-4.2.1.dist-info/RECORD
