Metadata-Version: 2.4
Name: invenio-assets
Version: 4.2.1
Summary: Media assets management for Invenio.
Home-page: https://github.com/inveniosoftware/invenio-assets
Author: CERN
Author-email: info@inveniosoftware.org
License: MIT
Keywords: invenio assets npm collect
Platform: any
Classifier: Development Status :: 5 - Production/Stable
Requires-Python: >=3.7
License-File: LICENSE
License-File: AUTHORS.rst
Requires-Dist: Flask-Collect-Invenio<2.0.0,>=1.4.0
Requires-Dist: Flask-WebpackExt<3.0.0,>=2.1.0
Requires-Dist: invenio-base<3.0.0,>=2.0.0
Provides-Extra: tests
Requires-Dist: pytest-black-ng>=0.4.0; extra == "tests"
Requires-Dist: pytest-invenio<4.0.0,>=3.0.0; extra == "tests"
Requires-Dist: mock>=1.3.0; extra == "tests"
Requires-Dist: sphinx>=4.5; extra == "tests"
Provides-Extra: docs
Dynamic: license-file
